<annotation>
	<folder>9</folder>
	<filename>f_40.jpg</filename>
	<path>C:\yolov5_base\workspace\training_demo\images\capsules_frame_sparse\9\f_40.jpg</path>
	<source>
		<database>Unknown</database>
	</source>
	<size>
		<width>851</width>
		<height>356</height>
		<depth>3</depth>
	</size>
	<segmented>0</segmented>
	<object>
		<name>capsule_9</name>
		<pose>Unspecified</pose>
		<truncated>0</truncated>
		<difficult>0</difficult>
		<bndbox>
			<xmin>278</xmin>
			<ymin>114</ymin>
			<xmax>434</xmax>
			<ymax>269</ymax>
		</bndbox>
	</object>
</annotation>
